Metadata-Version: 2.1
Name: example-lib-name
Version: 0.0.13
Summary: A description of your project
Home-page: UNKNOWN
License: UNKNOWN
Platform: UNKNOWN
